evaLEs/LE.py
evaLEs/__init__.py
evaLEs/numbaLE.py
evaLEs/numba_utils.py
evaLEs/utils.py
evaLEs-0.1.2.dist-info/LICENSE
evaLEs-0.1.2.dist-info/METADATA
evaLEs-0.1.2.dist-info/WHEEL
evaLEs-0.1.2.dist-info/top_level.txt
evaLEs-0.1.2.dist-info/RECORD
