Metadata-Version: 2.1
Name: evaLEs
Version: 0.1.2
Summary: Evaluate the Lyapunov Spectrum of a Dynamical System
Home-page: https://github.com/dodogabrie/evaLEs
Author: Edoardo Gabrielli
Author-email: dodogabrie97@live.it
License: GPLv3
Keywords: Lyapunov,LE,LyapunovExponents,LyapunovSpectrum
Platform: UNKNOWN
Requires-Dist: numba
Requires-Dist: numpy
Requires-Dist: scipy
Requires-Dist: setuptools
